<?xml version="1.0" encoding="UTF-8"?>
<ANCOR>
  <Trans scribe="Nicolas" audio_filename="1ap0296" version="3" version_date="031118">
    <Speakers>
      <Speaker id="spk1" name="hôtesse" check="no" type="female" dialect="native" accent="" scope="local" />
      <Speaker id="spk2" name="client" check="no" type="female" dialect="native" accent="" scope="local" />
    </Speakers>
    <Topics>
      <Topic id="to1" desc="1ap0296" />
    </Topics>
    <Episode>
      <Section type="report" startTime="0" endTime="16.161" topic="to1" id="1">
        <Turn startTime="0" endTime="0.945" speaker="spk1" id="1">
          <Sync time="0" />
          bonjour
        </Turn>
        <Turn speaker="spk2" startTime="0.945" endTime="5.376" id="2">
          <Sync time="0.945" />
          bonjour
          <anchor id="klunari_1329820603453" num="1">j'</anchor>
          aurais aimé avoir
          <anchor id="klunari_1329820610046" num="2">des renseignements</anchor>
          sur
          <anchor id="klunari_1329820624031" num="3">les sites</anchor>
          à visiter
          <anchor id="klunari_1329820640078" num="4">les châteaux</anchor>
        </Turn>
        <Turn speaker="spk1 spk2" startTime="5.376" endTime="6.741" id="3">
          <Sync time="5.376" />
          <Who nb="1" />
          oui bien sûr
          <Who nb="2" />
          les [pi]
        </Turn>
        <Turn speaker="spk1" startTime="6.741" endTime="12.049" id="4">
          <Sync time="6.741" />
          voilà donc ça c'est
          <anchor id="jmuzerelle_1340012276006" num="5">
            <anchor id="klunari_1331290253093" num="6">Grenoble</anchor>
            et
            <anchor id="klunari_1329820667796" num="7">l'agglomération</anchor>
            et
            <anchor id="klunari_1329820678984" num="8">le département</anchor>
          </anchor>
          même mais c'est
          <anchor id="klunari_1329820686437" num="9">
            un plan aussi de
            <anchor id="klunari_1329820693656" num="10">la ville</anchor>
          </anchor>
          hein
        </Turn>
        <Turn speaker="spk2" startTime="12.049" endTime="12.732" id="5">
          <Sync time="12.049" />
          merci
        </Turn>
        <Turn speaker="spk1" startTime="12.732" endTime="14.723" id="6">
          <Sync time="12.732" />
          mais
          <anchor id="klunari_1329820709375" num="11">je</anchor>
          <anchor id="klunari_1329820714328" num="12">vous</anchor>
          en prie
        </Turn>
        <Turn speaker="spk2" startTime="14.723" endTime="15.61" id="7">
          <Sync time="14.723" />
          au revoir
        </Turn>
        <Turn speaker="spk1" startTime="15.61" endTime="16.161" id="8">
          <Sync time="15.61" />
          au revoir
        </Turn>
      </Section>
    </Episode>
  </Trans>
  <annotations>
    <metadata corpusHashcode="1497-67323267" />
    <unit id="klunari_1329820603453">
      <characterisation>
        <type>PR</type>
        <featureSet>
          <feature name="GEN_REF">SPEC</feature>
          <feature name="NEW">NO</feature>
          <feature name="EN">PERS</feature>
          <feature name="DEF">DEF_SPLE</feature>
          <feature name="GP">NO</feature>
          <feature name="GENRE">F</feature>
          <feature name="NB">SG</feature>
          <feature name="CONTENT">j'</feature>
          <feature name="SPEAKER">spk2</feature>
          <feature name="PREVIOUS">bonjour</feature>
          <feature name="NEXT">aurais</feature>
        </featureSet>
      </characterisation>
    </unit>
    <unit id="klunari_1329820624031">
      <characterisation>
        <type>N</type>
        <featureSet>
          <feature name="GEN_REF">SPEC</feature>
          <feature name="NEW">YES</feature>
          <feature name="EN">NO</feature>
          <feature name="DEF">DEF_SPLE</feature>
          <feature name="GP">YES</feature>
          <feature name="GENRE">M</feature>
          <feature name="NB">PL</feature>
          <feature name="CONTENT">les sites</feature>
          <feature name="SPEAKER">spk2</feature>
          <feature name="PREVIOUS">sur</feature>
          <feature name="NEXT">à</feature>
        </featureSet>
      </characterisation>
    </unit>
    <unit id="klunari_1329820640078">
      <characterisation>
        <type>N</type>
        <featureSet>
          <feature name="GEN_REF">SPEC</feature>
          <feature name="NEW">YES</feature>
          <feature name="EN">NO</feature>
          <feature name="DEF">DEF_SPLE</feature>
          <feature name="GP">NO</feature>
          <feature name="GENRE">M</feature>
          <feature name="NB">PL</feature>
          <feature name="CONTENT">les châteaux</feature>
          <feature name="SPEAKER">spk2</feature>
          <feature name="PREVIOUS">visiter</feature>
          <feature name="NEXT">$</feature>
        </featureSet>
      </characterisation>
    </unit>
    <unit id="klunari_1329820667796">
      <characterisation>
        <type>N</type>
        <featureSet>
          <feature name="GEN_REF">SPEC</feature>
          <feature name="NEW">YES</feature>
          <feature name="EN">LOC</feature>
          <feature name="DEF">DEF_SPLE</feature>
          <feature name="GP">NO</feature>
          <feature name="GENRE">F</feature>
          <feature name="NB">SG</feature>
          <feature name="CONTENT">l'agglomération</feature>
          <feature name="SPEAKER">spk1</feature>
          <feature name="PREVIOUS">et</feature>
          <feature name="NEXT">et</feature>
        </featureSet>
      </characterisation>
    </unit>
    <unit id="klunari_1329820678984">
      <characterisation>
        <type>N</type>
        <featureSet>
          <feature name="GEN_REF">SPEC</feature>
          <feature name="NEW">YES</feature>
          <feature name="EN">NO</feature>
          <feature name="DEF">DEF_SPLE</feature>
          <feature name="GP">NO</feature>
          <feature name="GENRE">M</feature>
          <feature name="NB">SG</feature>
          <feature name="CONTENT">le département</feature>
          <feature name="SPEAKER">spk1</feature>
          <feature name="PREVIOUS">et</feature>
          <feature name="NEXT">même</feature>
        </featureSet>
      </characterisation>
    </unit>
    <unit id="klunari_1329820693656">
      <characterisation>
        <type>N</type>
        <featureSet>
          <feature name="GEN_REF">SPEC</feature>
          <feature name="NEW">NO</feature>
          <feature name="EN">LOC</feature>
          <feature name="DEF">DEF_SPLE</feature>
          <feature name="GP">YES</feature>
          <feature name="GENRE">F</feature>
          <feature name="NB">SG</feature>
          <feature name="CONTENT">la ville</feature>
          <feature name="SPEAKER">spk1</feature>
          <feature name="PREVIOUS">de</feature>
          <feature name="NEXT">hein</feature>
        </featureSet>
      </characterisation>
    </unit>
    <unit id="klunari_1329820709375">
      <characterisation>
        <type>PR</type>
        <featureSet>
          <feature name="GEN_REF">SPEC</feature>
          <feature name="NEW">NO</feature>
          <feature name="EN">PERS</feature>
          <feature name="DEF">DEF_SPLE</feature>
          <feature name="GP">NO</feature>
          <feature name="GENRE">F</feature>
          <feature name="NB">SG</feature>
          <feature name="CONTENT">je</feature>
          <feature name="SPEAKER">spk1</feature>
          <feature name="PREVIOUS">mais</feature>
          <feature name="NEXT">vous</feature>
        </featureSet>
      </characterisation>
    </unit>
    <unit id="klunari_1329820714328">
      <characterisation>
        <type>PR</type>
        <featureSet>
          <feature name="GEN_REF">SPEC</feature>
          <feature name="NEW">NO</feature>
          <feature name="EN">PERS</feature>
          <feature name="DEF">DEF_SPLE</feature>
          <feature name="GP">NO</feature>
          <feature name="GENRE">F</feature>
          <feature name="NB">SG</feature>
          <feature name="CONTENT">vous</feature>
          <feature name="SPEAKER">spk1</feature>
          <feature name="PREVIOUS">je</feature>
          <feature name="NEXT">en</feature>
        </featureSet>
      </characterisation>
    </unit>
    <unit id="klunari_1331290253093">
      <characterisation>
        <type>N</type>
        <featureSet>
          <feature name="NEW">YES</feature>
          <feature name="GEN_REF">SPEC</feature>
          <feature name="EN">LOC</feature>
          <feature name="DEF">DEF_SPLE</feature>
          <feature name="GP">NO</feature>
          <feature name="GENRE">UNK</feature>
          <feature name="NB">UNK</feature>
          <feature name="CONTENT">Grenoble</feature>
          <feature name="SPEAKER">spk1</feature>
          <feature name="PREVIOUS">est</feature>
          <feature name="NEXT">et</feature>
        </featureSet>
      </characterisation>
    </unit>
    <unit id="klunari_1329820610046">
      <characterisation>
        <type>N</type>
        <featureSet>
          <feature name="GEN_REF">SPEC</feature>
          <feature name="NEW">YES</feature>
          <feature name="EN">NO</feature>
          <feature name="DEF">INDEF</feature>
          <feature name="GP">NO</feature>
          <feature name="GENRE">M</feature>
          <feature name="NB">PL</feature>
          <feature name="CONTENT">des renseignements</feature>
          <feature name="SPEAKER">spk2</feature>
          <feature name="PREVIOUS">avoir</feature>
          <feature name="NEXT">sur</feature>
        </featureSet>
      </characterisation>
    </unit>
    <unit id="klunari_1329820686437">
      <characterisation>
        <type>N</type>
        <featureSet>
          <feature name="GEN_REF">SPEC</feature>
          <feature name="NEW">YES</feature>
          <feature name="EN">NO</feature>
          <feature name="DEF">INDEF</feature>
          <feature name="GP">NO</feature>
          <feature name="GENRE">M</feature>
          <feature name="NB">SG</feature>
          <feature name="CONTENT">un plan aussi de la ville</feature>
          <feature name="SPEAKER">spk1</feature>
          <feature name="PREVIOUS">est</feature>
          <feature name="NEXT">hein</feature>
        </featureSet>
      </characterisation>
    </unit>
    <unit id="jmuzerelle_1340012276006">
      <characterisation>
        <type>N</type>
        <featureSet>
          <feature name="GEN_REF">SPEC</feature>
          <feature name="NEW">YES</feature>
          <feature name="EN">LOC</feature>
          <feature name="DEF">DEF_SPLE</feature>
          <feature name="GP">NO</feature>
          <feature name="GENRE">M</feature>
          <feature name="NB">PL</feature>
          <feature name="CONTENT">Grenoble et l'agglomération et le département</feature>
          <feature name="SPEAKER">spk1</feature>
          <feature name="PREVIOUS">est</feature>
          <feature name="NEXT">même</feature>
        </featureSet>
      </characterisation>
    </unit>
    <relation id="sduchon_1339854365724">
      <characterisation>
        <type>INDIRECTE</type>
        <featureSet>
          <feature name="ID_LOC">YES</feature>
          <feature name="NOMBRE">UNK</feature>
          <feature name="GENRE">UNK</feature>
          <feature name="Distance_Turn">0</feature>
          <feature name="Distance_Mention">4</feature>
          <feature name="Distance_Char">69</feature>
          <feature name="Distance_Word">12</feature>
        </featureSet>
      </characterisation>
      <positioning>
        <term id="klunari_1329820693656" />
        <term id="klunari_1331290253093" />
      </positioning>
    </relation>
    <relation id="jmuzerelle_1340012310753">
      <characterisation>
        <type>ASSOC</type>
        <featureSet>
          <feature name="ID_LOC">YES</feature>
          <feature name="NOMBRE">YES</feature>
          <feature name="GENRE">YES</feature>
          <feature name="Distance_Turn">0</feature>
          <feature name="Distance_Mention">1</feature>
          <feature name="Distance_Char">9</feature>
          <feature name="Distance_Word">2</feature>
        </featureSet>
      </characterisation>
      <positioning>
        <term id="klunari_1329820640078" />
        <term id="klunari_1329820624031" />
      </positioning>
    </relation>
  </annotations>
</ANCOR>
