<?xml version="1.0" encoding="UTF-8"?>
<ANCOR>
  <Trans scribe="Nicolas" audio_filename="1ap0133" version="1" version_date="010912">
    <Speakers>
      <Speaker id="spk1" name="hôtesse" check="no" type="female" dialect="native" accent="" scope="local" />
      <Speaker id="spk2" name="client" check="no" type="female" dialect="native" accent="" scope="local" />
    </Speakers>
    <Topics>
      <Topic id="to1" desc="1ap0133" />
    </Topics>
    <Episode>
      <Section type="report" startTime="0" endTime="6.304" topic="to1" id="1">
        <Turn startTime="0" endTime="0.678" speaker="spk1 spk2" id="1">
          <Sync time="0" />
          <Who nb="1" />
          bonjour
          <Who nb="2" />
          bonjour
        </Turn>
        <Turn speaker="spk2" startTime="0.678" endTime="3.709" id="2">
          <Sync time="0.678" />
          est ce que
          <anchor id="sduchon_1340550627000" num="1">vous</anchor>
          avez
          <anchor id="sduchon_1340549457780" num="2">
            <anchor id="jmuzerelle_1370868428622" num="3">le plan</anchor>
            <anchor id="sduchon_1340551446355" num="4">du bus</anchor>
          </anchor>
          et
          <anchor id="sduchon_1340549460650" num="5">du TAG</anchor>
        </Turn>
        <Turn speaker="spk1 spk2" startTime="3.709" endTime="4.531" id="3">
          <Sync time="3.709" />
          <Who nb="1" />
          en face
          <Who nb="2" />
          s'il vous plaît
        </Turn>
        <Turn speaker="spk1" startTime="4.531" endTime="5.797" id="4">
          <Sync time="4.531" />
          <anchor id="jmuzerelle_1369143572145" num="6">c'</anchor>
          est
          <anchor id="sduchon_1340549852475" num="7">
            le bureau
            <anchor id="jmuzerelle_1369143547746" num="8">TAG</anchor>
          </anchor>
          <anchor id="sduchon_1341219263092" num="9">qui</anchor>
          est juste en face
        </Turn>
        <Turn speaker="spk2" startTime="5.797" endTime="6.304" id="5">
          <Sync time="5.797" />
          ah d'accord
        </Turn>
      </Section>
    </Episode>
  </Trans>
  <annotations>
    <metadata corpusHashcode="1131-79222077" />
    <unit id="sduchon_1340549460650">
      <characterisation>
        <type>N</type>
        <featureSet>
          <feature name="GEN_REF">SPEC</feature>
          <feature name="NEW">YES</feature>
          <feature name="EN">ORG</feature>
          <feature name="DEF">DEF_SPLE</feature>
          <feature name="GP">YES</feature>
          <feature name="GENRE">M</feature>
          <feature name="NB">SG</feature>
          <feature name="CONTENT">du TAG</feature>
          <feature name="SPEAKER">spk2</feature>
          <feature name="PREVIOUS">et</feature>
          <feature name="NEXT">$</feature>
        </featureSet>
      </characterisation>
    </unit>
    <unit id="sduchon_1340549852475">
      <characterisation>
        <type>N</type>
        <featureSet>
          <feature name="GEN_REF">SPEC</feature>
          <feature name="NEW">YES</feature>
          <feature name="EN">NO</feature>
          <feature name="DEF">DEF_SPLE</feature>
          <feature name="GP">NO</feature>
          <feature name="GENRE">M</feature>
          <feature name="NB">SG</feature>
          <feature name="CONTENT">le bureau TAG</feature>
          <feature name="SPEAKER">spk1</feature>
          <feature name="PREVIOUS">est</feature>
          <feature name="NEXT">qui</feature>
        </featureSet>
      </characterisation>
    </unit>
    <unit id="sduchon_1340550627000">
      <characterisation>
        <type>PR</type>
        <featureSet>
          <feature name="GEN_REF">SPEC</feature>
          <feature name="NEW">NO</feature>
          <feature name="EN">PERS</feature>
          <feature name="DEF">DEF_SPLE</feature>
          <feature name="GP">NO</feature>
          <feature name="GENRE">F</feature>
          <feature name="NB">SG</feature>
          <feature name="CONTENT">vous</feature>
          <feature name="SPEAKER">spk2</feature>
          <feature name="PREVIOUS">que</feature>
          <feature name="NEXT">avez</feature>
        </featureSet>
      </characterisation>
    </unit>
    <unit id="sduchon_1340551446355">
      <characterisation>
        <type>N</type>
        <featureSet>
          <feature name="GEN_REF">SPEC</feature>
          <feature name="NEW">YES</feature>
          <feature name="EN">NO</feature>
          <feature name="DEF">DEF_SPLE</feature>
          <feature name="GP">YES</feature>
          <feature name="GENRE">M</feature>
          <feature name="NB">SG</feature>
          <feature name="CONTENT">du bus</feature>
          <feature name="SPEAKER">spk2</feature>
          <feature name="PREVIOUS">plan</feature>
          <feature name="NEXT">et</feature>
        </featureSet>
      </characterisation>
    </unit>
    <unit id="sduchon_1341219263092">
      <characterisation>
        <type>PR</type>
        <featureSet>
          <feature name="NEW">NO</feature>
          <feature name="GEN_REF">SPEC</feature>
          <feature name="EN">NO</feature>
          <feature name="DEF">DEF_SPLE</feature>
          <feature name="GP">NO</feature>
          <feature name="GENRE">M</feature>
          <feature name="NB">SG</feature>
          <feature name="CONTENT">qui</feature>
          <feature name="SPEAKER">spk1</feature>
          <feature name="PREVIOUS">bureau</feature>
          <feature name="NEXT">est</feature>
        </featureSet>
      </characterisation>
    </unit>
    <unit id="sduchon_1340549457780">
      <characterisation>
        <type>N</type>
        <featureSet>
          <feature name="GEN_REF">SPEC</feature>
          <feature name="NEW">YES</feature>
          <feature name="EN">NO</feature>
          <feature name="DEF">DEF_SPLE</feature>
          <feature name="GP">NO</feature>
          <feature name="GENRE">M</feature>
          <feature name="NB">SG</feature>
          <feature name="CONTENT">le plan du bus</feature>
          <feature name="SPEAKER">spk2</feature>
          <feature name="PREVIOUS">avez</feature>
          <feature name="NEXT">et</feature>
        </featureSet>
      </characterisation>
    </unit>
    <unit id="jmuzerelle_1369143547746">
      <characterisation>
        <type>N</type>
        <featureSet>
          <feature name="NEW">NO</feature>
          <feature name="GEN_REF">SPEC</feature>
          <feature name="EN">ORG</feature>
          <feature name="DEF">DEF_SPLE</feature>
          <feature name="GP">NO</feature>
          <feature name="GENRE">M</feature>
          <feature name="NB">SG</feature>
          <feature name="CONTENT">TAG</feature>
          <feature name="SPEAKER">spk1</feature>
          <feature name="PREVIOUS">bureau</feature>
          <feature name="NEXT">qui</feature>
        </featureSet>
      </characterisation>
    </unit>
    <unit id="jmuzerelle_1369143572145">
      <characterisation>
        <type>PR</type>
        <featureSet>
          <feature name="NEW">YES</feature>
          <feature name="GEN_REF">SPEC</feature>
          <feature name="EN">NO</feature>
          <feature name="DEF">DEF_DEM</feature>
          <feature name="GP">NO</feature>
          <feature name="GENRE">M</feature>
          <feature name="NB">PL</feature>
          <feature name="CONTENT">c'</feature>
          <feature name="SPEAKER">spk1</feature>
          <feature name="PREVIOUS">^</feature>
          <feature name="NEXT">est</feature>
        </featureSet>
      </characterisation>
    </unit>
    <unit id="jmuzerelle_1370868428622">
      <characterisation>
        <type>N</type>
        <featureSet>
          <feature name="GEN_REF">SPEC</feature>
          <feature name="NEW">YES</feature>
          <feature name="EN">NO</feature>
          <feature name="DEF">DEF_SPLE</feature>
          <feature name="GP">NO</feature>
          <feature name="GENRE">M</feature>
          <feature name="NB">SG</feature>
          <feature name="CONTENT">le plan</feature>
          <feature name="SPEAKER">spk2</feature>
          <feature name="PREVIOUS">avez</feature>
          <feature name="NEXT">du</feature>
        </featureSet>
      </characterisation>
    </unit>
    <relation id="sduchon_1342691885895">
      <characterisation>
        <type>DIRECTE</type>
        <featureSet>
          <feature name="ID_LOC">NO</feature>
          <feature name="NOMBRE">YES</feature>
          <feature name="GENRE">YES</feature>
          <feature name="Distance_Turn">2</feature>
          <feature name="Distance_Mention">3</feature>
          <feature name="Distance_Char">39</feature>
          <feature name="Distance_Word">9</feature>
        </featureSet>
      </characterisation>
      <positioning>
        <term id="jmuzerelle_1369143547746" />
        <term id="sduchon_1340549460650" />
      </positioning>
    </relation>
    <relation id="sduchon_1342691897014">
      <characterisation>
        <type>ANAPHORE</type>
        <featureSet>
          <feature name="ID_LOC">YES</feature>
          <feature name="NOMBRE">YES</feature>
          <feature name="GENRE">YES</feature>
          <feature name="Distance_Turn">0</feature>
          <feature name="Distance_Mention">2</feature>
          <feature name="Distance_Char">0</feature>
          <feature name="Distance_Word">0</feature>
        </featureSet>
      </characterisation>
      <positioning>
        <term id="sduchon_1341219263092" />
        <term id="sduchon_1340549852475" />
      </positioning>
    </relation>
    <relation id="jmuzerelle_1369143579886">
      <characterisation>
        <type>ASSOC_PRONOM</type>
        <featureSet>
          <feature name="ID_LOC">NO</feature>
          <feature name="NOMBRE">NO</feature>
          <feature name="GENRE">YES</feature>
          <feature name="Distance_Turn">2</feature>
          <feature name="Distance_Mention">4</feature>
          <feature name="Distance_Char">32</feature>
          <feature name="Distance_Word">8</feature>
        </featureSet>
      </characterisation>
      <positioning>
        <term id="jmuzerelle_1369143572145" />
        <term id="sduchon_1340549457780" />
      </positioning>
    </relation>
    <relation id="jmuzerelle_1370868462488">
      <characterisation>
        <type>ASSOC_PRONOM</type>
        <featureSet>
          <feature name="ID_LOC">NO</feature>
          <feature name="NOMBRE">NO</feature>
          <feature name="GENRE">YES</feature>
          <feature name="Distance_Turn">0</feature>
          <feature name="Distance_Mention">0</feature>
          <feature name="Distance_Char">0</feature>
          <feature name="Distance_Word">0</feature>
        </featureSet>
      </characterisation>
      <positioning>
        <term id="jmuzerelle_1369143572145" />
        <term id="jmuzerelle_1370868433866" />
      </positioning>
    </relation>
    <schema id="jmuzerelle_1370868433866">
      <metadata>
        <author>jmuzerelle</author>
        <creation-date>1370868433866</creation-date>
        <lastModifier>jmuzerelle</lastModifier>
        <lastModificationDate>1370868435862</lastModificationDate>
      </metadata>
      <characterisation>
        <type>default</type>
        <featureSet>
          <feature name="default">default</feature>
        </featureSet>
      </characterisation>
      <positioning>
        <embedded-unit id="jmuzerelle_1370868428622" />
        <embedded-unit id="sduchon_1340549460650" />
      </positioning>
    </schema>
  </annotations>
</ANCOR>
