<?xml version="1.0" encoding="UTF-8"?>
<ANCOR>
  <Trans scribe="Nicolas" audio_filename="1nr0592" version="3" version_date="031203">
    <Topics>
      <Topic id="to1" desc="1nr0592" />
    </Topics>
    <Speakers>
      <Speaker id="spk1" name="hôtesse" check="no" type="female" dialect="native" accent="" scope="local" />
      <Speaker id="spk2" name="client" check="no" type="male" dialect="native" accent="" scope="local" />
    </Speakers>
    <Episode>
      <Section type="report" startTime="0" endTime="8.545" topic="to1" id="1">
        <Turn startTime="0" endTime="0.282" speaker="spk1" id="1">
          <Sync time="0" />
          bonjour
        </Turn>
        <Turn speaker="spk2" startTime="0.282" endTime="3.722" id="2">
          <Sync time="0.282" />
          <anchor id="gpascault_1350571425350" num="1">je</anchor>
          voulais savoir s'
          <anchor id="gpascault_1350571446161" num="2">il</anchor>
          existe
          <anchor id="gpascault_1350571467908" num="3">
            un plan
            <anchor id="gpascault_1350571501546" num="4">
              des pistes cyclables de
              <anchor id="gpascault_1350571569472" num="5">Grenoble</anchor>
            </anchor>
          </anchor>
        </Turn>
        <Turn speaker="spk1" startTime="3.722" endTime="7.26" id="3">
          <Sync time="3.722" />
          bien sûr ouais
        </Turn>
        <Turn speaker="spk2" startTime="7.26" endTime="7.983" id="4">
          <Sync time="7.26" />
          merci
        </Turn>
        <Turn speaker="spk1" startTime="7.983" endTime="8.545" id="5">
          <Sync time="7.983" />
          mais
          <anchor id="gpascault_1350571587360" num="6">je</anchor>
          <anchor id="gpascault_1350571590867" num="7">vous</anchor>
          en prie
        </Turn>
      </Section>
    </Episode>
  </Trans>
  <annotations>
    <metadata corpusHashcode="1047-79392060" />
    <unit id="gpascault_1350571425350">
      <characterisation>
        <type>PR</type>
        <featureSet>
          <feature name="GEN_REF">SPEC</feature>
          <feature name="NEW">NO</feature>
          <feature name="EN">PERS</feature>
          <feature name="DEF">DEF_SPLE</feature>
          <feature name="GP">NO</feature>
          <feature name="GENRE">M</feature>
          <feature name="NB">SG</feature>
          <feature name="CONTENT">je</feature>
          <feature name="SPEAKER">spk2</feature>
          <feature name="PREVIOUS">^</feature>
          <feature name="NEXT">voulais</feature>
        </featureSet>
      </characterisation>
    </unit>
    <unit id="gpascault_1350571446161">
      <characterisation>
        <type>PR</type>
        <featureSet>
          <feature name="GEN_REF">NULL</feature>
          <feature name="NEW">NO</feature>
          <feature name="EN">NO</feature>
          <feature name="DEF">EXPL</feature>
          <feature name="GP">NO</feature>
          <feature name="GENRE">M</feature>
          <feature name="NB">SG</feature>
          <feature name="CONTENT">il</feature>
          <feature name="SPEAKER">spk2</feature>
          <feature name="PREVIOUS">s'</feature>
          <feature name="NEXT">existe</feature>
        </featureSet>
      </characterisation>
    </unit>
    <unit id="gpascault_1350571467908">
      <characterisation>
        <type>N</type>
        <featureSet>
          <feature name="GEN_REF">SPEC</feature>
          <feature name="NEW">YES</feature>
          <feature name="EN">NO</feature>
          <feature name="DEF">INDEF</feature>
          <feature name="GP">NO</feature>
          <feature name="GENRE">M</feature>
          <feature name="NB">SG</feature>
          <feature name="CONTENT">un plan des pistes cyclables de Grenoble</feature>
          <feature name="SPEAKER">spk2</feature>
          <feature name="PREVIOUS">existe</feature>
          <feature name="NEXT">$</feature>
        </featureSet>
      </characterisation>
    </unit>
    <unit id="gpascault_1350571501546">
      <characterisation>
        <type>N</type>
        <featureSet>
          <feature name="GEN_REF">SPEC</feature>
          <feature name="NEW">YES</feature>
          <feature name="EN">NO</feature>
          <feature name="DEF">DEF_SPLE</feature>
          <feature name="GP">YES</feature>
          <feature name="GENRE">F</feature>
          <feature name="NB">PL</feature>
          <feature name="CONTENT">des pistes cyclables de Grenoble</feature>
          <feature name="SPEAKER">spk2</feature>
          <feature name="PREVIOUS">plan</feature>
          <feature name="NEXT">$</feature>
        </featureSet>
      </characterisation>
    </unit>
    <unit id="gpascault_1350571569472">
      <characterisation>
        <type>N</type>
        <featureSet>
          <feature name="GEN_REF">SPEC</feature>
          <feature name="NEW">YES</feature>
          <feature name="EN">LOC</feature>
          <feature name="DEF">DEF_SPLE</feature>
          <feature name="GP">YES</feature>
          <feature name="GENRE">UNK</feature>
          <feature name="NB">UNK</feature>
          <feature name="CONTENT">Grenoble</feature>
          <feature name="SPEAKER">spk2</feature>
          <feature name="PREVIOUS">de</feature>
          <feature name="NEXT">$</feature>
        </featureSet>
      </characterisation>
    </unit>
    <unit id="gpascault_1350571587360">
      <characterisation>
        <type>PR</type>
        <featureSet>
          <feature name="GEN_REF">SPEC</feature>
          <feature name="NEW">NO</feature>
          <feature name="EN">PERS</feature>
          <feature name="DEF">DEF_SPLE</feature>
          <feature name="GP">NO</feature>
          <feature name="GENRE">F</feature>
          <feature name="NB">SG</feature>
          <feature name="CONTENT">je</feature>
          <feature name="SPEAKER">spk1</feature>
          <feature name="PREVIOUS">mais</feature>
          <feature name="NEXT">vous</feature>
        </featureSet>
      </characterisation>
    </unit>
    <unit id="gpascault_1350571590867">
      <characterisation>
        <type>PR</type>
        <featureSet>
          <feature name="GEN_REF">SPEC</feature>
          <feature name="NEW">NO</feature>
          <feature name="EN">PERS</feature>
          <feature name="DEF">DEF_SPLE</feature>
          <feature name="GP">NO</feature>
          <feature name="GENRE">M</feature>
          <feature name="NB">SG</feature>
          <feature name="CONTENT">vous</feature>
          <feature name="SPEAKER">spk1</feature>
          <feature name="PREVIOUS">je</feature>
          <feature name="NEXT">en</feature>
        </featureSet>
      </characterisation>
    </unit>
  </annotations>
</ANCOR>
